{
  "kind": "collectionType",
  "collectionName": "platforms",
  "info": {
    "name": "Platform",
    "description": ""
  },
  "options": {
    "increments": true,
    "timestamps": true,
    "draftAndPublish": true
  },
  "pluginOptions": {},
  "attributes": {
    "name": {
      "type": "string",
      "required": true,
      "unique": true
    },
    "description": {
      "type": "richtext"
    },
    "thumbnail": {
      "model": "file",
      "via": "related",
      "allowedTypes": [
        "images"
      ],
      "plugin": "upload",
      "required": false,
      "pluginOptions": {}
    },
    "slogan": {
      "type": "string"
    }
  }
}
